rejot_contract/__init__.py
rejot_contract/consumer_schema.py
rejot_contract/public_schema.py
rejot_contract-0.2.1.dist-info/METADATA
rejot_contract-0.2.1.dist-info/WHEEL
rejot_contract-0.2.1.dist-info/licenses/LICENSE
rejot_contract-0.2.1.dist-info/RECORD
