Metadata-Version: 2.4
Name: rejot-contract
Version: 0.2.1
Summary: ReJot contracts for Python
Project-URL: Homepage, https://github.com/rejot-dev/rejot
Project-URL: Issues, https://github.com/rejot-dev/rejot/issues
Author-email: ReJot <rejot@rejot.dev>
License-Expression: Apache-2.0
License-File: LICENSE
Classifier: Operating System :: OS Independent
Classifier: Programming Language :: Python :: 3
Requires-Python: >=3.9
Requires-Dist: pydantic<3.0.0,>=2.0.0
